[
  {
    "title": "Half Time",
    "genre": "R&B",
    "artist": "Amy Winehouse",
    "imageUrl":"Covers/HalfTime.png",
    "id": "div1"
  },
  {
    "title": "Loner",
    "genre": "Soul",
    "artist": "Kali Uchis",
    "id": "2"
  },
  {
    "title": "What Kind of Love",
    "genre": "Soul",
    "artist": "Childish Gambino",
    "id": "3"
  },
  {
    "title": "Hate Me",
    "genre": "R&B",
    "artist": "Ellie Goulding",
    "id": "4"
  },
  {
    "title": "Build God, Then We'll Talk",
    "genre": "Punk Pop",
    "artist": "Panic! at the Disco",
    "image": "BuildGod.png",
    "id": "5"
  },
  {
    "title": "Without Me",
    "artist": "Halsey",
    "id": "6"
  },
  {
   "title": "SKELETONS",
    "genre": "Indie",
    "artist": "Travis Scott",
    "id":"7"
  },
  {
    "title": "134340",
    "genre": "K-pop",
    "artist":"BTS",
    "id":"8"
  },
  {
    "title": "Roses",
    "genre": "R&B",
    "artist":"Jaehyun",
    "id":"9"
  },
  {
    "title": "Tiramisu",
    "genre": "R&B",
    "artist":"Don Toliver",
    "id":"10"
  },
  {
    "title": "COFFEE BEAN",
    "genre": "Rap",
    "artist":"Travis Scott",
    "id":"11"
  },
  {
    "title": "N Side",
    "genre": "R&B",
    "artist":"Steve Lacy",
    "id":"12"
  },
  {
    "title": "I Won't Cry Anymore",
    "genre": "Soul",
    "artist":"Marvin Gaye",
    "id":"13"
  },
  {
    "title": "Faucet Failure",
    "genre": "Trap",
    "artist":"Ski Mask The Slump God",
    "id":"14"
  },
  {
    "title": "Catch Me Outside",
    "genre": "Trap",
    "artist":"Ski Mask The Slump God",
    "id":"15"
  },
  {
    "title": "UKA UKA",
    "genre": "Punk Pop",
    "artist":"Trippie Redd",
    "id":"16"
  },
{
    "title": "Missed Calls",
    "genre": "Hip Pop",
    "artist":"Mac Miller",
    "image":"MissedCalls.jpg",
    "id":"17" 
},
{ 
    "title": "Losing You",
    "genre": "R&B",
    "artist":"Solange",
    "image":"LosingYou.jpg",
    "id":"18"
},
{
    "title": "Jodie",
    "genre": "Soul",
    "artist":"SZA",
    "image":"CtrlSZA.webp",
    "id":"19"
},
{
  "title": "Love Lost",
    "genre": "Rap",
    "artist":"Mac Miller",
    "image":"",
    "id":"20"
},
{
  "title": "Sitting On Top of the World",
    "genre": "Rap",
    "artist":"Burna Baby",
    "image":"",
    "id":"21"
}
]